cst_lsp/__init__.py
cst_lsp/server.py
cst_lsp/code_actions/__init__.py
cst_lsp/code_actions/base.py
cst_lsp/code_actions/extract_method.py
cst_lsp/code_actions/import_symbol.py
cst_lsp/code_actions/variable_collector.py
cst_lsp/symbols/symbol_finder.py
cst_lsp-0.1.3.dist-info/LICENSE
cst_lsp-0.1.3.dist-info/METADATA
cst_lsp-0.1.3.dist-info/WHEEL
cst_lsp-0.1.3.dist-info/entry_points.txt
cst_lsp-0.1.3.dist-info/top_level.txt
cst_lsp-0.1.3.dist-info/RECORD
