Metadata-Version: 2.1
Name: cst-lsp
Version: 0.1.3
Author-email: Roy Williams <roy.williams.iii@gmail.com>
License: MIT
Classifier: Development Status :: 4 - Beta
Classifier: Topic :: Text Editors :: Integrated Development Environments (IDE)
Requires-Python: >=3.10
License-File: LICENSE
Requires-Dist: libcst >=1.4.0
Requires-Dist: pygls >=1.3.1
Provides-Extra: dev
Requires-Dist: pytest >=8.2.2 ; extra == 'dev'
Requires-Dist: ruff >=0.4.0 ; extra == 'dev'
Requires-Dist: pyright >=1.1.0 ; extra == 'dev'
